MANIFEST.in
setup.py
nostrain/__init__.py
nostrain.egg-info/PKG-INFO
nostrain.egg-info/SOURCES.txt
nostrain.egg-info/dependency_links.txt
nostrain.egg-info/top_level.txt
nostrain/sphinx/nostrain/theme.conf
nostrain/sphinx/nostrain/static/nasty_fabric.png
nostrain/sphinx/nostrain/static/nostrain.css_t