Metadata-Version: 1.0
Name: nostrain
Version: 0.1.2
Summary: Themes for sphinx and sublime text.
Home-page: https://github.com/gregoryv/nostrain
Author: Gregory Vincic
Author-email: g@7de.se
License: GPLv3
Platform: UNKNOWN
